scipion_testrunner/__init__.py
scipion_testrunner/__main__.py
scipion_testrunner/application/__init__.py
scipion_testrunner/application/cli.py
scipion_testrunner/application/logger.py
scipion_testrunner/configuration/__init__.py
scipion_testrunner/configuration/test_config.py
scipion_testrunner/configuration/test_data_keys.py
scipion_testrunner/domain/__init__.py
scipion_testrunner/domain/handlers/__init__.py
scipion_testrunner/domain/handlers/python_handler.py
scipion_testrunner/domain/handlers/scipion_handler.py
scipion_testrunner/domain/handlers/shell_handler.py
scipion_testrunner/domain/test_service.py
scipion_testrunner-1.0.1.dist-info/LICENSE
scipion_testrunner-1.0.1.dist-info/METADATA
scipion_testrunner-1.0.1.dist-info/WHEEL
scipion_testrunner-1.0.1.dist-info/entry_points.txt
scipion_testrunner-1.0.1.dist-info/RECORD
