Metadata-Version: 2.1
Name: scipion-testrunner
Version: 1.0.1
Summary: Module to handle in an efficient way the execution of Scipion tests
License: LICENSE
Keywords: scipion,testing
Author: Martín Salinas
Author-email: ssalinasmartin@gmail.com
Requires-Python: >=3.8,<4.0
Classifier: License :: Other/Proprietary License
Classifier: Programming Language :: Python :: 3
Classifier: Programming Language :: Python :: 3.8
Classifier: Programming Language :: Python :: 3.9
Classifier: Programming Language :: Python :: 3.10
Classifier: Programming Language :: Python :: 3.11
Classifier: Programming Language :: Python :: 3.12
